{
	"agcgw_all":{
		"CN":"connect-drcn.dbankcloud.cn",
		"CN_back":"connect-drcn.hispace.hicloud.com",
		"DE":"connect-dre.dbankcloud.cn",
		"DE_back":"connect-dre.hispace.hicloud.com",
		"RU":"connect-drru.dbankcloud.cn",
		"RU_back":"connect-drru.hispace.hicloud.com",
		"SG":"connect-dra.dbankcloud.cn",
		"SG_back":"connect-dra.hispace.hicloud.com"
	},
	"client":{
		"cp_id":"2640062000021180871",
		"product_id":"737518067794438242",
		"client_id":"813655478297971904",
		"client_secret":"6CAC777B473B9D7115EDE980664AE69339C806A3387B667488226A01666A42EB",
		"project_id":"737518067794438242",
		"app_id":"105441493",
		"api_key":"DAEDADeoI5ilunTNW/wqejrmFEGlfuiJxsucxTqCycBbKcW3JaDESXADnEDEtoB/Ef5Zz4pTZiGYPCINP13yNxW4X8EvVWEgM/4XrA==",
		"package_name":"id.ac.binus.wiktionic"
	},
	"oauth_client":{
		"client_id":"105441493",
		"client_type":1
	},
	"app_info":{
		"app_id":"105441493",
		"package_name":"id.ac.binus.wiktionic"
	},
	"configuration_version":"3.0",
	"appInfos":[
		{
			"package_name":"id.ac.binus.wiktionic",
			"client":{
				"app_id":"105441493"
			},
			"app_info":{
				"package_name":"id.ac.binus.wiktionic",
				"app_id":"105441493"
			},
			"oauth_client":{
				"client_type":1,
				"client_id":"105441493"
			}
		}
	]
}